<?xml version="1.0" encoding="UTF-8"?>
<MetaDataObject xmlns="http://v8.1c.ru/8.3/MDClasses" xmlns:app="http://v8.1c.ru/8.2/managed-application/core" xmlns:cfg="http://v8.1c.ru/8.1/data/enterprise/current-config" xmlns:cmi="http://v8.1c.ru/8.2/managed-application/cmi" xmlns:ent="http://v8.1c.ru/8.1/data/enterprise" xmlns:lf="http://v8.1c.ru/8.2/managed-application/logform" xmlns:style="http://v8.1c.ru/8.1/data/ui/style" xmlns:sys="http://v8.1c.ru/8.1/data/ui/fonts/system" xmlns:v8="http://v8.1c.ru/8.1/data/core" xmlns:v8ui="http://v8.1c.ru/8.1/data/ui" xmlns:web="http://v8.1c.ru/8.1/data/ui/colors/web" xmlns:win="http://v8.1c.ru/8.1/data/ui/colors/windows" xmlns:xen="http://v8.1c.ru/8.3/xcf/enums" xmlns:xpr="http://v8.1c.ru/8.3/xcf/predef" xmlns:xr="http://v8.1c.ru/8.3/xcf/readable" xmlns:xs="http://www.w3.org/2001/XMLSchema" xmlns:xsi="http://www.w3.org/2001/XMLSchema-instance" version="2.20">
	<ExternalDataProcessor uuid="af5d6724-7e30-4ef2-81e7-6c98c81e2ca8">
		<InternalInfo>
			<xr:ContainedObject>
				<xr:ClassId>c3831ec8-d8d5-4f93-8a22-f9bfae07327f</xr:ClassId>
				<xr:ObjectId>d3834177-16c4-466d-a081-5b1e9d05011e</xr:ObjectId>
			</xr:ContainedObject>
			<xr:GeneratedType name="ExternalDataProcessorObject.ФормаРМКУпрощенная" category="Object">
				<xr:TypeId>e8aa6bce-0470-4d41-add9-4ddfc4f4f658</xr:TypeId>
				<xr:ValueId>0aed9dfe-a583-44b7-bc10-3c0504e31d34</xr:ValueId>
			</xr:GeneratedType>
		</InternalInfo>
		<Properties>
			<Name>ФормаРМКУпрощенная</Name>
			<Synonym>
				<v8:item>
					<v8:lang>ru</v8:lang>
					<v8:content>Форма РМКУпрощенная</v8:content>
				</v8:item>
			</Synonym>
			<Comment/>
			<DefaultForm>ExternalDataProcessor.ФормаРМКУпрощенная.Form.Форма</DefaultForm>
			<AuxiliaryForm/>
		</Properties>
		<ChildObjects>
			<Attribute uuid="34c5755b-7e6b-4f3e-81fd-046aeb11a498">
				<Properties>
					<Name>ЭтоПриходныйЧек</Name>
					<Synonym>
						<v8:item>
							<v8:lang>ru</v8:lang>
							<v8:content>Это приходный чек</v8:content>
						</v8:item>
					</Synonym>
					<Comment/>
					<Type>
						<v8:Type>xs:boolean</v8:Type>
					</Type>
					<PasswordMode>false</PasswordMode>
					<Format/>
					<EditFormat/>
					<ToolTip/>
					<MarkNegatives>false</MarkNegatives>
					<Mask/>
					<MultiLine>false</MultiLine>
					<ExtendedEdit>false</ExtendedEdit>
					<MinValue xsi:nil="true"/>
					<MaxValue xsi:nil="true"/>
					<FillChecking>DontCheck</FillChecking>
					<ChoiceFoldersAndItems>Items</ChoiceFoldersAndItems>
					<ChoiceParameterLinks/>
					<ChoiceParameters/>
					<QuickChoice>Auto</QuickChoice>
					<CreateOnInput>Auto</CreateOnInput>
					<ChoiceForm/>
					<LinkByType/>
					<ChoiceHistoryOnInput>Auto</ChoiceHistoryOnInput>
				</Properties>
			</Attribute>
			<Attribute uuid="830eeb1d-67fa-4e25-9235-203e6feb65c6">
				<Properties>
					<Name>Организация</Name>
					<Synonym>
						<v8:item>
							<v8:lang>ru</v8:lang>
							<v8:content>Организация</v8:content>
						</v8:item>
					</Synonym>
					<Comment/>
					<Type>
						<v8:TypeSet>cfg:DefinedType.ОрганизацияРМК</v8:TypeSet>
					</Type>
					<PasswordMode>false</PasswordMode>
					<Format/>
					<EditFormat/>
					<ToolTip/>
					<MarkNegatives>false</MarkNegatives>
					<Mask/>
					<MultiLine>false</MultiLine>
					<ExtendedEdit>false</ExtendedEdit>
					<MinValue xsi:nil="true"/>
					<MaxValue xsi:nil="true"/>
					<FillChecking>DontCheck</FillChecking>
					<ChoiceFoldersAndItems>Items</ChoiceFoldersAndItems>
					<ChoiceParameterLinks/>
					<ChoiceParameters/>
					<QuickChoice>Auto</QuickChoice>
					<CreateOnInput>Auto</CreateOnInput>
					<ChoiceForm/>
					<LinkByType/>
					<ChoiceHistoryOnInput>Auto</ChoiceHistoryOnInput>
				</Properties>
			</Attribute>
			<Attribute uuid="1ae6462e-e3a5-42f5-861a-6fdce76d6607">
				<Properties>
					<Name>Кассир</Name>
					<Synonym>
						<v8:item>
							<v8:lang>ru</v8:lang>
							<v8:content>Кассир</v8:content>
						</v8:item>
					</Synonym>
					<Comment/>
					<Type>
						<v8:TypeSet>cfg:DefinedType.КассирРМК</v8:TypeSet>
					</Type>
					<PasswordMode>false</PasswordMode>
					<Format/>
					<EditFormat/>
					<ToolTip/>
					<MarkNegatives>false</MarkNegatives>
					<Mask/>
					<MultiLine>false</MultiLine>
					<ExtendedEdit>false</ExtendedEdit>
					<MinValue xsi:nil="true"/>
					<MaxValue xsi:nil="true"/>
					<FillChecking>DontCheck</FillChecking>
					<ChoiceFoldersAndItems>Items</ChoiceFoldersAndItems>
					<ChoiceParameterLinks/>
					<ChoiceParameters/>
					<QuickChoice>Auto</QuickChoice>
					<CreateOnInput>Auto</CreateOnInput>
					<ChoiceForm/>
					<LinkByType/>
					<ChoiceHistoryOnInput>Auto</ChoiceHistoryOnInput>
				</Properties>
			</Attribute>
			<Attribute uuid="30331efe-f220-40d8-b2f3-1d71c919be51">
				<Properties>
					<Name>ЭтоОплатаКредита</Name>
					<Synonym>
						<v8:item>
							<v8:lang>ru</v8:lang>
							<v8:content>Это оплата кредита</v8:content>
						</v8:item>
					</Synonym>
					<Comment/>
					<Type>
						<v8:Type>xs:boolean</v8:Type>
					</Type>
					<PasswordMode>false</PasswordMode>
					<Format/>
					<EditFormat/>
					<ToolTip/>
					<MarkNegatives>false</MarkNegatives>
					<Mask/>
					<MultiLine>false</MultiLine>
					<ExtendedEdit>false</ExtendedEdit>
					<MinValue xsi:nil="true"/>
					<MaxValue xsi:nil="true"/>
					<FillChecking>DontCheck</FillChecking>
					<ChoiceFoldersAndItems>Items</ChoiceFoldersAndItems>
					<ChoiceParameterLinks/>
					<ChoiceParameters/>
					<QuickChoice>Auto</QuickChoice>
					<CreateOnInput>Auto</CreateOnInput>
					<ChoiceForm/>
					<LinkByType/>
					<ChoiceHistoryOnInput>Auto</ChoiceHistoryOnInput>
				</Properties>
			</Attribute>
			<Attribute uuid="694651cf-1b77-4627-a612-c184bc3804a2">
				<Properties>
					<Name>EmailПокупателя</Name>
					<Synonym>
						<v8:item>
							<v8:lang>ru</v8:lang>
							<v8:content>Email покупателя</v8:content>
						</v8:item>
					</Synonym>
					<Comment/>
					<Type>
						<v8:Type>xs:string</v8:Type>
						<v8:StringQualifiers>
							<v8:Length>0</v8:Length>
							<v8:AllowedLength>Variable</v8:AllowedLength>
						</v8:StringQualifiers>
					</Type>
					<PasswordMode>false</PasswordMode>
					<Format/>
					<EditFormat/>
					<ToolTip/>
					<MarkNegatives>false</MarkNegatives>
					<Mask/>
					<MultiLine>false</MultiLine>
					<ExtendedEdit>false</ExtendedEdit>
					<MinValue xsi:nil="true"/>
					<MaxValue xsi:nil="true"/>
					<FillChecking>DontCheck</FillChecking>
					<ChoiceFoldersAndItems>Items</ChoiceFoldersAndItems>
					<ChoiceParameterLinks/>
					<ChoiceParameters/>
					<QuickChoice>Auto</QuickChoice>
					<CreateOnInput>Auto</CreateOnInput>
					<ChoiceForm/>
					<LinkByType/>
					<ChoiceHistoryOnInput>Auto</ChoiceHistoryOnInput>
				</Properties>
			</Attribute>
			<Attribute uuid="84a39c0f-7f41-4c33-8f18-045cf4d9c7b7">
				<Properties>
					<Name>КассаККМ</Name>
					<Synonym>
						<v8:item>
							<v8:lang>ru</v8:lang>
							<v8:content>Касса ККМ</v8:content>
						</v8:item>
					</Synonym>
					<Comment/>
					<Type>
						<v8:TypeSet>cfg:DefinedType.КассаККМРМК</v8:TypeSet>
					</Type>
					<PasswordMode>false</PasswordMode>
					<Format/>
					<EditFormat/>
					<ToolTip/>
					<MarkNegatives>false</MarkNegatives>
					<Mask/>
					<MultiLine>false</MultiLine>
					<ExtendedEdit>false</ExtendedEdit>
					<MinValue xsi:nil="true"/>
					<MaxValue xsi:nil="true"/>
					<FillChecking>ShowError</FillChecking>
					<ChoiceFoldersAndItems>Items</ChoiceFoldersAndItems>
					<ChoiceParameterLinks/>
					<ChoiceParameters/>
					<QuickChoice>Auto</QuickChoice>
					<CreateOnInput>Auto</CreateOnInput>
					<ChoiceForm/>
					<LinkByType/>
					<ChoiceHistoryOnInput>Auto</ChoiceHistoryOnInput>
				</Properties>
			</Attribute>
			<Attribute uuid="8db2ad9c-65a6-4c15-9e93-cc0f956adcfa">
				<Properties>
					<Name>ФискальныйРегистратор</Name>
					<Synonym>
						<v8:item>
							<v8:lang>ru</v8:lang>
							<v8:content>Фискальный регистратор</v8:content>
						</v8:item>
					</Synonym>
					<Comment/>
					<Type>
						<v8:Type>cfg:CatalogRef.ПодключаемоеОборудование</v8:Type>
					</Type>
					<PasswordMode>false</PasswordMode>
					<Format/>
					<EditFormat/>
					<ToolTip/>
					<MarkNegatives>false</MarkNegatives>
					<Mask/>
					<MultiLine>false</MultiLine>
					<ExtendedEdit>false</ExtendedEdit>
					<MinValue xsi:nil="true"/>
					<MaxValue xsi:nil="true"/>
					<FillChecking>DontCheck</FillChecking>
					<ChoiceFoldersAndItems>Items</ChoiceFoldersAndItems>
					<ChoiceParameterLinks/>
					<ChoiceParameters/>
					<QuickChoice>Auto</QuickChoice>
					<CreateOnInput>Auto</CreateOnInput>
					<ChoiceForm/>
					<LinkByType/>
					<ChoiceHistoryOnInput>Auto</ChoiceHistoryOnInput>
				</Properties>
			</Attribute>
			<TabularSection uuid="a0c97a36-129a-4ac0-ae46-8c01da17e9e1">
				<InternalInfo>
					<xr:GeneratedType name="DataProcessorTabularSection.ФормаРМКУпрощенная.ПозицииЧека" category="TabularSection">
						<xr:TypeId>ac53826e-8df8-4c72-988b-c9ad93ac384d</xr:TypeId>
						<xr:ValueId>01241660-20be-4909-bc6b-47a306f1435e</xr:ValueId>
					</xr:GeneratedType>
					<xr:GeneratedType name="DataProcessorTabularSectionRow.ФормаРМКУпрощенная.ПозицииЧека" category="TabularSectionRow">
						<xr:TypeId>46fb3f4b-ba10-4b71-81e5-9fce50911c0a</xr:TypeId>
						<xr:ValueId>00208b29-75b4-4a41-bcbe-25bec02052ee</xr:ValueId>
					</xr:GeneratedType>
				</InternalInfo>
				<Properties>
					<Name>ПозицииЧека</Name>
					<Synonym>
						<v8:item>
							<v8:lang>ru</v8:lang>
							<v8:content>Позиции чека</v8:content>
						</v8:item>
					</Synonym>
					<Comment/>
					<ToolTip/>
					<FillChecking>DontCheck</FillChecking>
					<StandardAttributes>
						<xr:StandardAttribute name="LineNumber">
							<xr:LinkByType/>
							<xr:FillChecking>DontCheck</xr:FillChecking>
							<xr:MultiLine>false</xr:MultiLine>
							<xr:FillFromFillingValue>false</xr:FillFromFillingValue>
							<xr:CreateOnInput>Auto</xr:CreateOnInput>
							<xr:TypeReductionMode>TransformValues</xr:TypeReductionMode>
							<xr:MaxValue xsi:nil="true"/>
							<xr:ToolTip/>
							<xr:ExtendedEdit>false</xr:ExtendedEdit>
							<xr:Format/>
							<xr:ChoiceForm/>
							<xr:QuickChoice>Auto</xr:QuickChoice>
							<xr:ChoiceHistoryOnInput>Auto</xr:ChoiceHistoryOnInput>
							<xr:EditFormat/>
							<xr:PasswordMode>false</xr:PasswordMode>
							<xr:DataHistory>Use</xr:DataHistory>
							<xr:MarkNegatives>false</xr:MarkNegatives>
							<xr:MinValue xsi:nil="true"/>
							<xr:Synonym/>
							<xr:Comment/>
							<xr:FullTextSearch>Use</xr:FullTextSearch>
							<xr:ChoiceParameterLinks/>
							<xr:FillValue xsi:nil="true"/>
							<xr:Mask/>
							<xr:ChoiceParameters/>
						</xr:StandardAttribute>
					</StandardAttributes>
				</Properties>
				<ChildObjects>
					<Attribute uuid="527396b5-a21f-43a2-85fa-7a87e3460382">
						<Properties>
							<Name>Номенклатура</Name>
							<Synonym>
								<v8:item>
									<v8:lang>ru</v8:lang>
									<v8:content>Номенклатура</v8:content>
								</v8:item>
							</Synonym>
							<Comment/>
							<Type>
								<v8:Type>cfg:CatalogRef.Номенклатура</v8:Type>
							</Type>
							<PasswordMode>false</PasswordMode>
							<Format/>
							<EditFormat/>
							<ToolTip/>
							<MarkNegatives>false</MarkNegatives>
							<Mask/>
							<MultiLine>false</MultiLine>
							<ExtendedEdit>false</ExtendedEdit>
							<MinValue xsi:nil="true"/>
							<MaxValue xsi:nil="true"/>
							<FillFromFillingValue>false</FillFromFillingValue>
							<FillValue xsi:nil="true"/>
							<FillChecking>DontCheck</FillChecking>
							<ChoiceFoldersAndItems>Items</ChoiceFoldersAndItems>
							<ChoiceParameterLinks/>
							<ChoiceParameters/>
							<QuickChoice>Auto</QuickChoice>
							<CreateOnInput>Auto</CreateOnInput>
							<ChoiceForm/>
							<LinkByType/>
							<ChoiceHistoryOnInput>Auto</ChoiceHistoryOnInput>
						</Properties>
					</Attribute>
					<Attribute uuid="156e1200-e64e-41fa-b85d-eef201548114">
						<Properties>
							<Name>Количество</Name>
							<Synonym>
								<v8:item>
									<v8:lang>ru</v8:lang>
									<v8:content>Количество</v8:content>
								</v8:item>
							</Synonym>
							<Comment/>
							<Type>
								<v8:TypeSet>cfg:DefinedType.Число15_3РМК</v8:TypeSet>
							</Type>
							<PasswordMode>false</PasswordMode>
							<Format/>
							<EditFormat/>
							<ToolTip/>
							<MarkNegatives>false</MarkNegatives>
							<Mask/>
							<MultiLine>false</MultiLine>
							<ExtendedEdit>false</ExtendedEdit>
							<MinValue xsi:nil="true"/>
							<MaxValue xsi:nil="true"/>
							<FillFromFillingValue>false</FillFromFillingValue>
							<FillValue xsi:nil="true"/>
							<FillChecking>DontCheck</FillChecking>
							<ChoiceFoldersAndItems>Items</ChoiceFoldersAndItems>
							<ChoiceParameterLinks/>
							<ChoiceParameters/>
							<QuickChoice>Auto</QuickChoice>
							<CreateOnInput>Auto</CreateOnInput>
							<ChoiceForm/>
							<LinkByType/>
							<ChoiceHistoryOnInput>Auto</ChoiceHistoryOnInput>
						</Properties>
					</Attribute>
					<Attribute uuid="edc073f3-3227-4dad-9376-d76ed3e0455c">
						<Properties>
							<Name>Цена</Name>
							<Synonym>
								<v8:item>
									<v8:lang>ru</v8:lang>
									<v8:content>Цена</v8:content>
								</v8:item>
							</Synonym>
							<Comment/>
							<Type>
								<v8:TypeSet>cfg:DefinedType.Число15_2РМК</v8:TypeSet>
							</Type>
							<PasswordMode>false</PasswordMode>
							<Format/>
							<EditFormat/>
							<ToolTip/>
							<MarkNegatives>false</MarkNegatives>
							<Mask/>
							<MultiLine>false</MultiLine>
							<ExtendedEdit>false</ExtendedEdit>
							<MinValue xsi:nil="true"/>
							<MaxValue xsi:nil="true"/>
							<FillFromFillingValue>false</FillFromFillingValue>
							<FillValue xsi:nil="true"/>
							<FillChecking>DontCheck</FillChecking>
							<ChoiceFoldersAndItems>Items</ChoiceFoldersAndItems>
							<ChoiceParameterLinks/>
							<ChoiceParameters/>
							<QuickChoice>Auto</QuickChoice>
							<CreateOnInput>Auto</CreateOnInput>
							<ChoiceForm/>
							<LinkByType/>
							<ChoiceHistoryOnInput>Auto</ChoiceHistoryOnInput>
						</Properties>
					</Attribute>
					<Attribute uuid="06b51a6e-6754-4c5d-9e73-410387b4c216">
						<Properties>
							<Name>Сумма</Name>
							<Synonym>
								<v8:item>
									<v8:lang>ru</v8:lang>
									<v8:content>Сумма</v8:content>
								</v8:item>
							</Synonym>
							<Comment/>
							<Type>
								<v8:TypeSet>cfg:DefinedType.Число15_2РМК</v8:TypeSet>
							</Type>
							<PasswordMode>false</PasswordMode>
							<Format/>
							<EditFormat/>
							<ToolTip/>
							<MarkNegatives>false</MarkNegatives>
							<Mask/>
							<MultiLine>false</MultiLine>
							<ExtendedEdit>false</ExtendedEdit>
							<MinValue xsi:nil="true"/>
							<MaxValue xsi:nil="true"/>
							<FillFromFillingValue>false</FillFromFillingValue>
							<FillValue xsi:nil="true"/>
							<FillChecking>DontCheck</FillChecking>
							<ChoiceFoldersAndItems>Items</ChoiceFoldersAndItems>
							<ChoiceParameterLinks/>
							<ChoiceParameters/>
							<QuickChoice>Auto</QuickChoice>
							<CreateOnInput>Auto</CreateOnInput>
							<ChoiceForm/>
							<LinkByType/>
							<ChoiceHistoryOnInput>Auto</ChoiceHistoryOnInput>
						</Properties>
					</Attribute>
					<Attribute uuid="4d208746-79e9-4721-9e6e-069fda0199ef">
						<Properties>
							<Name>ПредметРасчета</Name>
							<Synonym>
								<v8:item>
									<v8:lang>ru</v8:lang>
									<v8:content>Предмет расчета</v8:content>
								</v8:item>
							</Synonym>
							<Comment/>
							<Type>
								<v8:Type>cfg:EnumRef.ПризнакиПредметаРасчета</v8:Type>
							</Type>
							<PasswordMode>false</PasswordMode>
							<Format/>
							<EditFormat/>
							<ToolTip/>
							<MarkNegatives>false</MarkNegatives>
							<Mask/>
							<MultiLine>false</MultiLine>
							<ExtendedEdit>false</ExtendedEdit>
							<MinValue xsi:nil="true"/>
							<MaxValue xsi:nil="true"/>
							<FillFromFillingValue>false</FillFromFillingValue>
							<FillValue xsi:nil="true"/>
							<FillChecking>DontCheck</FillChecking>
							<ChoiceFoldersAndItems>Items</ChoiceFoldersAndItems>
							<ChoiceParameterLinks/>
							<ChoiceParameters/>
							<QuickChoice>Auto</QuickChoice>
							<CreateOnInput>Auto</CreateOnInput>
							<ChoiceForm/>
							<LinkByType/>
							<ChoiceHistoryOnInput>Auto</ChoiceHistoryOnInput>
						</Properties>
					</Attribute>
					<Attribute uuid="7c37fc97-190c-4147-a014-ec3daa2642fd">
						<Properties>
							<Name>СпособРасчета</Name>
							<Synonym>
								<v8:item>
									<v8:lang>ru</v8:lang>
									<v8:content>Способ расчета</v8:content>
								</v8:item>
							</Synonym>
							<Comment/>
							<Type>
								<v8:Type>cfg:EnumRef.ПризнакиСпособаРасчета</v8:Type>
							</Type>
							<PasswordMode>false</PasswordMode>
							<Format/>
							<EditFormat/>
							<ToolTip/>
							<MarkNegatives>false</MarkNegatives>
							<Mask/>
							<MultiLine>false</MultiLine>
							<ExtendedEdit>false</ExtendedEdit>
							<MinValue xsi:nil="true"/>
							<MaxValue xsi:nil="true"/>
							<FillFromFillingValue>false</FillFromFillingValue>
							<FillValue xsi:nil="true"/>
							<FillChecking>DontCheck</FillChecking>
							<ChoiceFoldersAndItems>Items</ChoiceFoldersAndItems>
							<ChoiceParameterLinks/>
							<ChoiceParameters/>
							<QuickChoice>Auto</QuickChoice>
							<CreateOnInput>Auto</CreateOnInput>
							<ChoiceForm/>
							<LinkByType/>
							<ChoiceHistoryOnInput>Auto</ChoiceHistoryOnInput>
						</Properties>
					</Attribute>
					<Attribute uuid="3ea6d168-2952-40f4-9ef4-85f0475fe8f9">
						<Properties>
							<Name>Договор</Name>
							<Synonym>
								<v8:item>
									<v8:lang>ru</v8:lang>
									<v8:content>Договор</v8:content>
								</v8:item>
							</Synonym>
							<Comment/>
							<Type>
								<v8:Type>cfg:CatalogRef.ДоговорыКонтрагентов</v8:Type>
							</Type>
							<PasswordMode>false</PasswordMode>
							<Format/>
							<EditFormat/>
							<ToolTip/>
							<MarkNegatives>false</MarkNegatives>
							<Mask/>
							<MultiLine>false</MultiLine>
							<ExtendedEdit>false</ExtendedEdit>
							<MinValue xsi:nil="true"/>
							<MaxValue xsi:nil="true"/>
							<FillFromFillingValue>false</FillFromFillingValue>
							<FillValue xsi:nil="true"/>
							<FillChecking>DontCheck</FillChecking>
							<ChoiceFoldersAndItems>Items</ChoiceFoldersAndItems>
							<ChoiceParameterLinks/>
							<ChoiceParameters/>
							<QuickChoice>Auto</QuickChoice>
							<CreateOnInput>Auto</CreateOnInput>
							<ChoiceForm/>
							<LinkByType/>
							<ChoiceHistoryOnInput>Auto</ChoiceHistoryOnInput>
						</Properties>
					</Attribute>
					<Attribute uuid="dfc509fc-3df6-47e0-a37d-f9dced0ddf26">
						<Properties>
							<Name>СтавкаНДС</Name>
							<Synonym>
								<v8:item>
									<v8:lang>ru</v8:lang>
									<v8:content>Ставка НДС</v8:content>
								</v8:item>
							</Synonym>
							<Comment/>
							<Type>
								<v8:Type>cfg:CatalogRef.СтавкиНДС</v8:Type>
							</Type>
							<PasswordMode>false</PasswordMode>
							<Format/>
							<EditFormat/>
							<ToolTip/>
							<MarkNegatives>false</MarkNegatives>
							<Mask/>
							<MultiLine>false</MultiLine>
							<ExtendedEdit>false</ExtendedEdit>
							<MinValue xsi:nil="true"/>
							<MaxValue xsi:nil="true"/>
							<FillFromFillingValue>false</FillFromFillingValue>
							<FillValue xsi:nil="true"/>
							<FillChecking>DontCheck</FillChecking>
							<ChoiceFoldersAndItems>Items</ChoiceFoldersAndItems>
							<ChoiceParameterLinks/>
							<ChoiceParameters/>
							<QuickChoice>Auto</QuickChoice>
							<CreateOnInput>Auto</CreateOnInput>
							<ChoiceForm/>
							<LinkByType/>
							<ChoiceHistoryOnInput>Auto</ChoiceHistoryOnInput>
						</Properties>
					</Attribute>
					<Attribute uuid="1240e7af-f8e9-4e39-a5e3-ad4ddf7a4fcf">
						<Properties>
							<Name>ИННПоставщика</Name>
							<Synonym>
								<v8:item>
									<v8:lang>ru</v8:lang>
									<v8:content>ИННПоставщика</v8:content>
								</v8:item>
							</Synonym>
							<Comment/>
							<Type>
								<v8:Type>xs:string</v8:Type>
								<v8:StringQualifiers>
									<v8:Length>12</v8:Length>
									<v8:AllowedLength>Variable</v8:AllowedLength>
								</v8:StringQualifiers>
							</Type>
							<PasswordMode>false</PasswordMode>
							<Format/>
							<EditFormat/>
							<ToolTip/>
							<MarkNegatives>false</MarkNegatives>
							<Mask/>
							<MultiLine>false</MultiLine>
							<ExtendedEdit>false</ExtendedEdit>
							<MinValue xsi:nil="true"/>
							<MaxValue xsi:nil="true"/>
							<FillFromFillingValue>false</FillFromFillingValue>
							<FillValue xsi:type="xs:string"/>
							<FillChecking>DontCheck</FillChecking>
							<ChoiceFoldersAndItems>Items</ChoiceFoldersAndItems>
							<ChoiceParameterLinks/>
							<ChoiceParameters/>
							<QuickChoice>Auto</QuickChoice>
							<CreateOnInput>Auto</CreateOnInput>
							<ChoiceForm/>
							<LinkByType/>
							<ChoiceHistoryOnInput>Auto</ChoiceHistoryOnInput>
						</Properties>
					</Attribute>
				</ChildObjects>
			</TabularSection>
			<Form>Форма</Form>
			<Template>МакетЧека</Template>
		</ChildObjects>
	</ExternalDataProcessor>
</MetaDataObject>